.gitignore
README.rst
ez_setup.py
setup.py
src/watchit/__init__.py
src/watchit/script.py
src/watchit.egg-info/PKG-INFO
src/watchit.egg-info/SOURCES.txt
src/watchit.egg-info/dependency_links.txt
src/watchit.egg-info/entry_points.txt
src/watchit.egg-info/not-zip-safe
src/watchit.egg-info/requires.txt
src/watchit.egg-info/top_level.txt