Metadata-Version: 1.0
Name: watchit
Version: 0.0.1
Summary: Watch a directory for file changes and exit
Home-page: https://github.com/jkenlooper/watchit
Author: Jake Hickenlooper
Author-email: jake@weboftomorrow.com
License: UNKNOWN
Platform: UNKNOWN
Classifier: Development Status :: 2 - Pre-Alpha
Classifier: Intended Audience :: Developers
Classifier: Intended Audience :: Information Technology
Classifier: License :: OSI Approved :: GNU General Public License v3 or later (GPLv3+)
Classifier: Natural Language :: English
Classifier: Operating System :: POSIX
Classifier: Programming Language :: Python :: 2.6
Classifier: Topic :: Software Development :: Build Tools
